edfi_lms_file_utils/__init__.py
edfi_lms_file_utils/constants.py
edfi_lms_file_utils/directory_repository.py
edfi_lms_file_utils/file_reader.py
edfi_lms_file_utils/file_repository.py
edfi_lms_file_utils/py.typed
edfi_lms_file_utils-1.0.6.dist-info/METADATA
edfi_lms_file_utils-1.0.6.dist-info/WHEEL
edfi_lms_file_utils-1.0.6.dist-info/RECORD
