Metadata-Version: 2.1
Name: edfi-lms-file-utils
Version: 1.0.6
Summary: Utilities to facilitate use of the filesystem created by Ed-Fi LMS Extractors
Home-page: https://docs.ed-fi.org/getting-started/edfi-exchange/technology/ed-fi-lms-toolkit
License: Apache-2.0
Author: Ed-Fi Alliance, LLC and contributors
Requires-Python: >=3.9,<4.0
Classifier: License :: OSI Approved :: Apache Software License
Classifier: Programming Language :: Python :: 3
Classifier: Programming Language :: Python :: 3.9
Classifier: Programming Language :: Python :: 3.10
Classifier: Programming Language :: Python :: 3.11
Classifier: Programming Language :: Python :: 3.12
Requires-Dist: numpy (>=1,<2)
Requires-Dist: pandas (<2.0.0)
Project-URL: Repository, https://github.com/Ed-Fi-Exchange-OSS/LMS-Toolkit
